Workbook

Sheet Overview
A1: PRISMA 2020 Screening Stage: Title and Abstract Screening (IC/EC Criteria)
A2: Full included and excluded record detail for Step 3 of the review pipeline
A4: Metric | B4: Value
A5: Records entering Step 3 (Step 2 survivors) | B5: 3089
A6: Total included after Step 3 | B6: =COUNTA(Included!A2:A142) -> 141
A7: Total excluded after Step 3 | B7: =COUNTA(Excluded!A2:A2949) -> 2948
A9: Exclusion breakdown by reason
A10: EC1 — No thematic match / outside subsection's 3–8 selectivity cap | B10: =COUNTIF(Excluded!G2:G2949,"*EC1*") -> 2790
A11: EC2 — Conference paper, book chapter, or conference report | B11: =COUNTIF(Excluded!G2:G2949,"*EC2*") -> 1
A12: EC3 — Not published in English (RIS language field) | B12: =COUNTIF(Excluded!G2:G2949,"*EC3*") -> 95
A13: EC4 — Published outside 2020–2026, not IC2-exempt | B13: =COUNTIF(Excluded!G2:G2949,"*EC4*") -> 3
A14: EC5 — No DOI on file (reclassified from EC1/EC3) | B14: =COUNTIF(Excluded!G2:G2949,"*EC5*") -> 59
A15: Sum of EC1–EC5 occurrences | B15: =SUM(B10:B14) -> 2948
A17: Records with no DOI on entry to Step 3
A18: Total no-DOI (of 3,089 entering Step 3) | B18: =COUNTA('No DOI Records'!A2:A60) -> 59
A19: — has a URL as fallback | B19: =COUNTIF('No DOI Records'!G2:G60, "Yes") -> 48
A20: — no URL either (highest risk) | B20: =COUNTIF('No DOI Records'!G2:G60, "No") -> 11
A21: — included after Step 3 | B21: =COUNTIF('No DOI Records'!H2:H60, "Included") -> 0
A22: — excluded after Step 3 | B22: =COUNTIF('No DOI Records'!H2:H60, "Excluded") -> 59
A24: Records retained by inclusion criterion
A25: IC1 | B25: =COUNTIF(Included!B2:B142,"IC1") -> 123
A26: IC2 | B26: =COUNTIF(Included!B2:B142,"IC2") -> 18
A27: Total retained | B27: =SUM(B25:B26) -> 141

Sheet Included
A1: No. | B1: IC Code | C1: Title | D1: Year | E1: Database | F1: DOI | G1: Journal / Venue
A2: 1 | B2: IC2 | C2: Internet of Things: A survey on machine learning-based intrusion detection approaches | D2: 2019 | E2: Scopus | F2: 10.1016/j.comnet.2019.01.023 | G2: Computer Networks
A3: 2 | B3: IC2 | C3: Network Intrusion Detection for IoT Security Based on Learning Techniques | D3: 2019 | E3: Scopus | F3: 10.1109/COMST.2019.2896380 | G3: IEEE Communications Surveys and Tutorials
A4: 3 | B4: IC1 | C4: Recent endeavors in machine learning-powered intrusion detection systems for the Internet of Things | D4: 2024 | E4: Scopus | F4: 10.1016/j.jnca.2024.103925 | G4: Journal of Network and Computer Applications
A5: 4 | B5: IC1 | C5: A comprehensive survey on deep learning-based intrusion detection systems in Internet of Things (IoT) | D5: 2025 | E5: Scopus | F5: 10.1111/exsy.13726 | G5: Expert Systems
A6: 5 | B6: IC1 | C6: A Survey of Deep Learning Technologies for Intrusion Detection in Internet of Things | D6: 2024 | E6: Scopus | F6: 10.1109/ACCESS.2023.3349287 | G6: IEEE Access
A7: 6 | B7: IC1 | C7: A Taxonomy of Machine-Learning-Based Intrusion Detection Systems for the Internet of Things: A Survey | D7: 2022 | E7: Scopus | F7: 10.1109/JIOT.2021.3126811 | G7: IEEE Internet of Things Journal
A8: 7 | B8: IC2 | C8: A survey on transfer learning | D8: 2010 | E8: Scopus | F8: 10.1109/TKDE.2009.191 | G8: IEEE Transactions on Knowledge and Data Engineering
A9: 8 | B9: IC2 | C9: Improving predictive inference under covariate shift by weighting the log-likelihood function | D9: 2000 | E9: Scopus | F9: 10.1016/s0378-3758(00)00115-4 | G9: Journal of Statistical Planning and Inference
A10: 9 | B10: IC2 | C10: A unifying view on dataset shift in classification | D10: 2012 | E10: Scopus | F10: 10.1016/j.patcog.2011.06.019 | G10: Pattern Recognition
A11: 10 | B11: IC1 | C11: Preventing dataset shift from breaking machine-learning biomarkers | D11: 2021 | E11: Scopus | F11: 10.1093/gigascience/giab055 | G11: GigaScience
A12: 11 | B12: IC1 | C12: A Survey of Unsupervised Deep Domain Adaptation | D12: 2020 | E12: Scopus | F12: 10.1145/3400066 | G12: ACM Transactions on Intelligent Systems and Technology
A13: 12 | B13: IC1 | C13: A Comprehensive Survey on Test-Time Adaptation Under Distribution Shifts | D13: 2025 | E13: Scopus | F13: 10.1007/s11263-024-02181-w | G13: International Journal of Computer Vision
... A87: 86 | B87: IC1 | C87: Secure and Explainable Federated Learning for IoT Intrusion Detection: A Comprehensive Survey | D87: 2026 | E87: WoS | F87: 10.1109/OJCOMS.2026.3681580 | G87: IEEE OPEN JOURNAL OF THE COMMUNICATIONS SOCIETY
A88: 87 | B88: IC2 | C88: MOA: Massive online analysis | D88: 2010 | E88: Scopus | G88: Journal of Machine Learning Research
A89: =A88+1 -> 88 | B89: IC1 | C89: Machine Learning-Enabled IoT Security: Open Issues and Challenges under Advanced Persistent Threats | D89: 2023 | E89: Scopus | F89: 10.1145/3530812 | G89: ACM Computing Surveys
A90: =A89+1 -> 89 | B90: IC1 | C90: Deep learning for intrusion detection in emerging technologies: a comprehensive survey and new perspectives | D90: 2025 | E90: Scopus | F90: 10.1007/s10462-025-11346-z | G90: Artificial Intelligence Review
A91: =A90+1 -> 90 | B91: IC1 | C91: Network intrusion datasets: A survey, limitations, and recommendations | D91: 2025 | E91: WoS | F91: 10.1016/j.cose.2025.104510 | G91: COMPUTERS & SECURITY
A92: =A91+1 -> 91 | B92: IC1 | C92: A Review on Machine Learning and Deep Learning Perspectives of IDS for IoT: Recent Updates, Security Issues, and Challenges | D92: 2021 | E92: Scopus | F92: 10.1007/s11831-020-09496-0 | G92: Archives of Computational Methods in Engineering
A93: =A92+1 -> 92 | B93: IC1 | C93: A critical review of intrusion detection systems in the internet of things: techniques, deployment strategy, validation strategy, attacks, public datasets and challenges | D93: 2021 | E93: Scopus | F93: 10.1186/s42400-021-00077-7 | G93: Cybersecurity
A94: =A93+1 -> 93 | B94: IC1 | C94: Adversarial Machine Learning for Network Intrusion Detection Systems: A Comprehensive Survey | D94: 2023 | E94: Scopus | F94: 10.1109/COMST.2022.3233793 | G94: IEEE Communications Surveys and Tutorials
A95: =A94+1 -> 94 | B95: IC1 | C95: Machine learning based solutions for security of Internet of Things (IoT): A survey | D95: 2020 | E95: WoS | F95: 10.1016/j.jnca.2020.102630 | G95: JOURNAL OF NETWORK AND COMPUTER APPLICATIONS
A96: =A95+1 -> 95 | B96: IC1 | C96: Generalization Error Bounds for Graph Neural Networks in Unseen Domains | D96: 2025 | E96: Scopus | F96: 10.1109/TAI.2025.3556978 | G96: IEEE Transactions on Artificial Intelligence
A97: =A96+1 -> 96 | B97: IC1 | C97: Towards Accurate and Robust Domain Adaptation Under Multiple Noisy Environments | D97: 2023 | E97: Scopus | F97: 10.1109/TPAMI.2022.3215150 | G97: IEEE Transactions on Pattern Analysis and Machine Intelligence
A98: =A97+1 -> 97 | B98: IC1 | C98: On the value of label and semantic information in domain generalization | D98: 2023 | E98: Scopus | F98: 10.1016/j.neunet.2023.03.023 | G98: Neural Networks
A99: =A98+1 -> 98 | B99: IC1 | C99: Dynamical Targeted Ensemble Learning for Streaming Data With Concept Drift | D99: 2024 | E99: Scopus | F99: 10.1109/TKDE.2024.3460404 | G99: IEEE Transactions on Knowledge and Data Engineering
A100: =A99+1 -> 99 | B100: IC1 | C100: Concept Drift Adaptation by Exploiting Drift Type | D100: 2024 | E100: Scopus | F100: 10.1145/3638777 | G100: ACM Transactions on Knowledge Discovery from Data
... A142: =A141+1 -> 141 | B142: IC1 | C142: A Decentralized Federated WGAN-GP Framework for Anomaly Detection in Industrial Control Systems | D142: 2026 | E142: Scopus | F142: 10.1109/ACCESS.2026.3704897 | G142: IEEE Access

Sheet Excluded
A1: No. | B1: Title | C1: Year | D1: Database | E1: DOI | F1: Journal / Venue | G1: Reason Code(s) | H1: Detail
A2: 1 | B2: Adversarial Machine Learning in IoT Security: A Comprehensive Survey | C2: 2026 | D2: Scopus | E2: 10.1145/3785665 | F2: ACM Computing Surveys | G2: EC1 | H2: Topically matched a thematic subsection (passed IC1/IC3/IC5, and IC4/no EC2-4 issue found) but was not retained as part of that subsection's primary-focus against more closely matching records; treated as EC1 (outside the primary focus this review's synthesis retains) on a comparative basis within its subsection.
A3: 2 | B3: Machine Learning for Cybersecurity: A Survey of Applications, Adversarial Challenges, and Future Research Directions | C3: 2025 | D3: Scopus | E3: 10.3390/electronics14234563 | F3: Electronics (Switzerland) | G3: EC1 | H3: Topically matched a thematic subsection (passed IC1/IC3/IC5, and IC4/no EC2-4 issue found) but was not retained as part of that subsection's primary-focus against more closely matching records; treated as EC1 (outside the primary focus this review's synthesis retains) on a comparative basis within its subsection.
A4: 3 | B4: Swarm intelligence in anomaly detection systems: an overview | C4: 2021 | D4: Scopus | E4: 10.1080/1206212X.2018.1521895 | F4: International Journal of Computers and Applications | G4: EC1 | H4: Topically matched a thematic subsection (passed IC1/IC3/IC5, and IC4/no EC2-4 issue found) but was not retained as part of that subsection's primary-focus against more closely matching records; treated as EC1 (outside the primary focus this review's synthesis retains) on a comparative basis within its subsection.
A5: 4 | B5: Generative AI in Intrusion Detection Systems for Internet of Things: A Systematic Literature Review | C5: 2025 | D5: Scopus | E5: 10.1109/OJCOMS.2025.3573194 | F5: IEEE Open Journal of the Communications Society | G5: EC1 | H5: Topically matched a thematic subsection (passed IC1/IC3/IC5, and IC4/no EC2-4 issue found) but was not retained as part of that subsection's primary-focus against more closely matching records; treated as EC1 (outside the primary focus this review's synthesis retains) on a comparative basis within its subsection.
A6: 5 | B6: A Literature Review Framework and Open Research Challenges for Predictive Maintenance in industry 4.0 | C6: 2025 | D6: Scopus | E6: 10.1016/j.cie.2025.111193 | F6: Computers and Industrial Engineering | G6: EC1 | H6: Topically matched a thematic subsection (passed IC1/IC3/IC5, and IC4/no EC2-4 issue found) but was not retained as part of that subsection's primary-focus against more closely matching records; treated as EC1 (outside the primary focus this review's synthesis retains) on a comparative basis within its subsection.
A7: 6 | B7: Review on Open-Source IoT and Edge-Compatible Devices for Health Monitoring Applications | C7: 2024 | D7: Scopus | E7: 10.18280/i2m.230307 | F7: Instrumentation Mesure Metrologie | G7: EC1 | H7: Topically matched a thematic subsection (passed IC1/IC3/IC5, and IC4/no EC2-4 issue found) but was not retained as part of that subsection's primary-focus against more closely matching records; treated as EC1 (outside the primary focus this review's synthesis retains) on a comparative basis within its subsection.
A8: 7 | B8: Intrusion detection systems for internet of thing based big data: a review | C8: 2023 | D8: Scopus | E8: 10.11591/ijres.v12.i1.pp87-96 | F8: International Journal of Reconfigurable and Embedded Systems | G8: EC1 | H8: Topically matched a thematic subsection (passed IC1/IC3/IC5, and IC4/no EC2-4 issue found) but was not retained as part of that subsection's primary-focus against more closely matching records; treated as EC1 (outside the primary focus this review's synthesis retains) on a comparative basis within its subsection.
A9: 8 | B9: Artificial Intelligence in Malware and Network Intrusion Detection: A Comprehensive Survey of Techniques, Datasets, Challenges, and Future Directions | C9: 2025 | D9: Scopus | E9: 10.58496/BJAI/2025/008 | F9: Babylonian Journal of Artificial Intelligence | G9: EC1 | H9: Topically matched a thematic subsection (passed IC1/IC3/IC5, and IC4/no EC2-4 issue found) but was not retained as part of that subsection's primary-focus against more closely matching records; treated as EC1 (outside the primary focus this review's synthesis retains) on a comparative basis within its subsection.
A10: 9 | B10: A systematic review on cybersecurity of robotic systems: vulnerabilities trends, threats, attacks, challenges, and proposed framework | C10: 2025 | D10: Scopus | E10: 10.1007/s10207-025-01041-z | F10: International Journal of Information Security | G10: EC1 | H10: Topically matched a thematic subsection (passed IC1/IC3/IC5, and IC4/no EC2-4 issue found) but was not retained as part of that subsection's primary-focus against more closely matching records; treated as EC1 (outside the primary focus this review's synthesis retains) on a comparative basis within its subsection.
A11: 10 | B11: DeepSense: A Physics-Guided Deep Learning Paradigm for Anomaly Detection in Soil Gas Data at Geologic CO2Storage Sites | C11: 2021 | D11: Scopus | E11: 10.1021/acs.est.1c04048 | F11: Environmental Science and Technology | G11: EC1 | H11: Topically matched a thematic subsection (passed IC1/IC3/IC5, and IC4/no EC2-4 issue found) but was not retained as part of that subsection's primary-focus against more closely matching records; treated as EC1 (outside the primary focus this review's synthesis retains) on a comparative basis within its subsection.
A12: 11 | B12: MLRA-Sec: an adaptive and intelligent cyber-security-assessment model for internet of medical things (IoMT) | C12: 2025 | D12: Scopus | E12: 10.1007/s10207-024-00923-y | F12: International Journal of Information Security | G12: EC1 | H12: Topically matched a thematic subsection (passed IC1/IC3/IC5, and IC4/no EC2-4 issue found) but was not retained as part of that subsection's primary-focus against more closely matching records; treated as EC1 (outside the primary focus this review's synthesis retains) on a comparative basis within its subsection.
A13: 12 | B13: A Survey on Hybrid-CNN and LLMs for Intrusion Detection Systems: Recent IoT Datasets | C13: 2024 | D13: Scopus | E13: 10.1109/ACCESS.2024.3506604 | F13: IEEE Access | G13: EC1 | H13: Topically matched a thematic subsection (passed IC1/IC3/IC5, and IC4/no EC2-4 issue found) but was not retained as part of that subsection's primary-focus against more closely matching records; treated as EC1 (outside the primary focus this review's synthesis retains) on a comparative basis within its subsection.
... A2887: 2886 | B2887: Intelligent Analysis Technologies for Encrypted Traffic: Current Status, Advances, and Challenges | C2887: 2026 | D2887: WoS | E2887: 10.11999/JEIT250416 | F2887: JOURNAL OF ELECTRONICS & INFORMATION TECHNOLOGY | G2887: EC3 | H2887: RIS language field indicates non-English publication (Chinese).
A2888: 2887 | B2888: A Systematic Approach to Prevent Threats Using IDS in IoT Based Devices | C2888: 2025 | D2888: Scopus | F2888: GMSARN International Journal | G2888: EC5 | H2888: Record has no DOI on file in its RIS export (and no independently accessible URL beyond a gated database results-page link). Reclassified as EC5 (full-text inaccessible / bibliographic details unverifiable) per user instruction; this replaces the record's original Step 3 exclusion reason (EC1), which is no longer shown.
A2889: 2888 | B2889: A REVIEW OF THE PARTICLE SWARM CLUSTERING METHOD FOR INTRUSION DETECTION IN IOT | C2889: 2022 | D2889: Scopus | F2889: Journal of Theoretical and Applied Information Technology | G2889: EC5 | H2889: Record has no DOI on file in its RIS export (and no independently accessible URL beyond a gated database results-page link). Reclassified as EC5 (full-text inaccessible / bibliographic details unverifiable) per user instruction; this replaces the record's original Step 3 exclusion reason (EC1), which is no longer shown.
A2890: 2889 | B2890: PERFORMANCE ANALYSIS OF INTRUSION DETECTION APPROACHES IN AGRICULTURAL IOT NETWORKS: A MACHINE LEARNING BASED APPROACH | C2890: 2023 | D2890: Scopus | F2890: Journal of Theoretical and Applied Information Technology | G2890: EC5 | H2890: Record has no DOI on file in its RIS export (and no independently accessible URL beyond a gated database results-page link). Reclassified as EC5 (full-text inaccessible / bibliographic details unverifiable) per user instruction; this replaces the record's original Step 3 exclusion reason (EC1), which is no longer shown.
A2891: 2890 | B2891: A comprehensive analysis on intrusion detection in iot based smart environments using machine learning approaches | C2891: 2020 | D2891: Scopus | F2891: International Journal of Scientific and Technology Research | G2891: EC5 | H2891: Record has no DOI on file in its RIS export (and no independently accessible URL beyond a gated database results-page link). Reclassified as EC5 (full-text inaccessible / bibliographic details unverifiable) per user instruction; this replaces the record's original Step 3 exclusion reason (EC1), which is no longer shown.
A2892: 2891 | B2892: Pave Your Own Path: Graph Gradual Domain Adaptation on Fused Gromov-Wasserstein Geodesics | C2892: 2026 | D2892: Scopus | F2892: Transactions on Machine Learning Research | G2892: EC5 | H2892: Record has no DOI on file in its RIS export (and no independently accessible URL beyond a gated database results-page link). Reclassified as EC5 (full-text inaccessible / bibliographic details unverifiable) per user instruction; this replaces the record's original Step 3 exclusion reason (EC1), which is no longer shown.
A2893: 2892 | B2893: Point-Identification of a Robust Predictor Under Latent Shift with Imperfect Proxies | C2893: 2026 | D2893: Scopus | F2893: Transactions on Machine Learning Research | G2893: EC5 | H2893: Record has no DOI on file in its RIS export (and no independently accessible URL beyond a gated database results-page link). Reclassified as EC5 (full-text inaccessible / bibliographic details unverifiable) per user instruction; this replaces the record's original Step 3 exclusion reason (EC1), which is no longer shown.
A2894: 2893 | B2894: Quantifying Context Bias in Domain Adaptation for Object Detection | C2894: 2025 | D2894: Scopus | F2894: Transactions on Machine Learning Research | G2894: EC5 | H2894: Record has no DOI on file in its RIS export (and no independently accessible URL beyond a gated database results-page link). Reclassified as EC5 (full-text inaccessible / bibliographic details unverifiable) per user instruction; this replaces the record's original Step 3 exclusion reason (EC1), which is no longer shown.
A2895: 2894 | B2895: Multi-view Handwritten Character Recognition Method with Adversarial Domain Adaptation and Momentum Prototype Fusion | C2895: 2026 | D2895: Scopus | F2895: IAENG International Journal of Computer Science | G2895: EC5 | H2895: Record has no DOI on file in its RIS export (and no independently accessible URL beyond a gated database results-page link). Reclassified as EC5 (full-text inaccessible / bibliographic details unverifiable) per user instruction; this replaces the record's original Step 3 exclusion reason (EC1), which is no longer shown.
A2896: 2895 | B2896: Recall and Refine: A Simple but Effective Source-free Open-set Domain Adaptation Framework | C2896: 2025 | D2896: Scopus | F2896: Transactions on Machine Learning Research | G2896: EC5 | H2896: Record has no DOI on file in its RIS export (and no independently accessible URL beyond a gated database results-page link). Reclassified as EC5 (full-text inaccessible / bibliographic details unverifiable) per user instruction; this replaces the record's original Step 3 exclusion reason (EC1), which is no longer shown.
A2897: 2896 | B2897: Precise High-Dimensional Asymptotics for Quantifying Heterogeneous Transfers | C2897: 2025 | D2897: Scopus | F2897: Journal of Machine Learning Research | G2897: EC5 | H2897: Record has no DOI on file in its RIS export (and no independently accessible URL beyond a gated database results-page link). Reclassified as EC5 (full-text inaccessible / bibliographic details unverifiable) per user instruction; this replaces the record's original Step 3 exclusion reason (EC1), which is no longer shown.
A2898: 2897 | B2898: Time Series Domain Adaptation via Channel-Selective Representation Alignment | C2898: 2025 | D2898: Scopus | F2898: Transactions on Machine Learning Research | G2898: EC5 | H2898: Record has no DOI on file in its RIS export (and no independently accessible URL beyond a gated database results-page link). Reclassified as EC5 (full-text inaccessible / bibliographic details unverifiable) per user instruction; this replaces the record's original Step 3 exclusion reason (EC1), which is no longer shown.
A2899: 2898 | B2899: Latent Covariate Shift: Unlocking Partial Identifiability for Multi-Source Domain Adaptation | C2899: 2025 | D2899: Scopus | F2899: Transactions on Machine Learning Research | G2899: EC5 | H2899: Record has no DOI on file in its RIS export (and no independently accessible URL beyond a gated database results-page link). Reclassified as EC5 (full-text inaccessible / bibliographic details unverifiable) per user instruction; this replaces the record's original Step 3 exclusion reason (EC1), which is no longer shown.
... A2943: 2942 | B2943: Effectiveness of Tree-based Ensembles for Anomaly Discovery: Insights, Batch and Streaming Active Learning | C2943: 2024 | D2943: WoS | F2943: JOURNAL OF ARTIFICIAL INTELLIGENCE RESEARCH | G2943: EC5 | H2943: Record has no DOI on file in its RIS export (and no independently accessible URL beyond a gated database results-page link). Reclassified as EC5 (full-text inaccessible / bibliographic details unverifiable) per user instruction; this replaces the record's original Step 3 exclusion reason (EC1), which is no longer shown.
A2944: 2943 | B2944: Adversarial Machine Learning in IoT Security: A Comprehensive Survey | C2944: 2026 | D2944: Scopus | E2944: 10.1145/3785665 | F2944: ACM Computing Surveys | G2944: EC1 | H2944: Topically matched a thematic subsection (passed IC1/IC3/IC5, and IC4/no EC2-4 issue found) but was not retained as part of that subsection's primary-focus against more closely matching records; treated as EC1 (outside the primary focus this review's synthesis retains) on a comparative basis within its subsection.
A2945: 2944 | B2945: A Systematic Approach to Prevent Threats Using IDS in IoT Based Devices | C2945: 2025 | D2945: Scopus | F2945: GMSARN International Journal | G2945: EC5 | H2945: Record has no DOI on file in its RIS export (and no independently accessible URL beyond a gated database results-page link). Reclassified as EC5 (full-text inaccessible / bibliographic details unverifiable) per user instruction; this replaces the record's original Step 3 exclusion reason (EC1), which is no longer shown.
A2946: 2945 | B2946: A REVIEW OF THE PARTICLE SWARM CLUSTERING METHOD FOR INTRUSION DETECTION IN IOT | C2946: 2022 | D2946: Scopus | F2946: Journal of Theoretical and Applied Information Technology | G2946: EC5 | H2946: Record has no DOI on file in its RIS export (and no independently accessible URL beyond a gated database results-page link). Reclassified as EC5 (full-text inaccessible / bibliographic details unverifiable) per user instruction; this replaces the record's original Step 3 exclusion reason (EC1), which is no longer shown.
A2947: 2946 | B2947: PERFORMANCE ANALYSIS OF INTRUSION DETECTION APPROACHES IN AGRICULTURAL IOT NETWORKS: A MACHINE LEARNING BASED APPROACH | C2947: 2023 | D2947: Scopus | F2947: Journal of Theoretical and Applied Information Technology | G2947: EC5 | H2947: Record has no DOI on file in its RIS export (and no independently accessible URL beyond a gated database results-page link). Reclassified as EC5 (full-text inaccessible / bibliographic details unverifiable) per user instruction; this replaces the record's original Step 3 exclusion reason (EC1), which is no longer shown.
A2948: 2947 | B2948: Federated Learning-Based Model to Lightweight IDSs for Heterogeneous IoT Networks: State-of-the-Art, Challenges, and Future Directions | C2948: 2024 | D2948: Scopus | E2948: 10.1109/ACCESS.2024.3460468 | F2948: IEEE Access | G2948: EC1 | H2948: Topically matched a thematic subsection (passed IC1/IC3/IC5, and IC4/no EC2-4 issue found) but was not retained as part of that subsection's primary-focus against more closely matching records; treated as EC1 (outside the primary focus this review's synthesis retains) on a comparative basis within its subsection.
A2949: 2948 | B2949: Replay or regret: Evaluating continual learning methods for robust intrusion detection | C2949: 2025 | D2949: WoS | E2949: 10.1109/MILCOM64451.2025.11310341 | F2949: IEEE Military Communications | G2949: EC1 | H2949: Topically matched a thematic subsection (passed IC1/IC3/IC5, and IC4/no EC2-4 issue found) but was not retained as part of that subsection's primary-focus against more closely matching records; treated as EC1 (outside the primary focus this review's synthesis retains) on a comparative basis within its subsection.

Sheet No DOI Records
A1: No. | B1: Title | C1: Year | D1: Database | E1: Journal / Venue | F1: URL | G1: Has URL? | H1: Step 3 Status
A2: 1 | B2: A Systematic Approach to Prevent Threats Using IDS in IoT Based Devices | C2: 2025 | D2: Scopus | E2: GMSARN International Journal | F2: https://www.scopus.com/pages/publications/85195447719?origin=resultslist | G2: Yes | H2: Excluded
A3: 2 | B3: A REVIEW OF THE PARTICLE SWARM CLUSTERING METHOD FOR INTRUSION DETECTION IN IOT | C3: 2022 | D3: Scopus | E3: Journal of Theoretical and Applied Information Technology | F3: https://www.scopus.com/pages/publications/85131760782?origin=resultslist | G3: Yes | H3: Excluded
A4: 3 | B4: PERFORMANCE ANALYSIS OF INTRUSION DETECTION APPROACHES IN AGRICULTURAL IOT NETWORKS: A MACHINE LEARNING BASED APPROACH | C4: 2023 | D4: Scopus | E4: Journal of Theoretical and Applied Information Technology | F4: https://www.scopus.com/pages/publications/85179414237?origin=resultslist | G4: Yes | H4: Excluded
A5: 4 | B5: A comprehensive analysis on intrusion detection in iot based smart environments using machine learning approaches | C5: 2020 | D5: Scopus | E5: International Journal of Scientific and Technology Research | F5: https://www.scopus.com/pages/publications/85083508136?origin=resultslist | G5: Yes | H5: Excluded
A6: 5 | B6: Pave Your Own Path: Graph Gradual Domain Adaptation on Fused Gromov-Wasserstein Geodesics | C6: 2026 | D6: Scopus | E6: Transactions on Machine Learning Research | F6: https://www.scopus.com/pages/publications/105030113875?origin=resultslist | G6: Yes | H6: Excluded
A7: 6 | B7: Point-Identification of a Robust Predictor Under Latent Shift with Imperfect Proxies | C7: 2026 | D7: Scopus | E7: Transactions on Machine Learning Research | F7: https://www.scopus.com/pages/publications/105041121289?origin=resultslist | G7: Yes | H7: Excluded
A8: 7 | B8: Quantifying Context Bias in Domain Adaptation for Object Detection | C8: 2025 | D8: Scopus | E8: Transactions on Machine Learning Research | F8: https://www.scopus.com/pages/publications/105028596287?origin=resultslist | G8: Yes | H8: Excluded
A9: 8 | B9: Multi-view Handwritten Character Recognition Method with Adversarial Domain Adaptation and Momentum Prototype Fusion | C9: 2026 | D9: Scopus | E9: IAENG International Journal of Computer Science | F9: https://www.scopus.com/pages/publications/105040796793?origin=resultslist | G9: Yes | H9: Excluded
A10: 9 | B10: Recall and Refine: A Simple but Effective Source-free Open-set Domain Adaptation Framework | C10: 2025 | D10: Scopus | E10: Transactions on Machine Learning Research | F10: https://www.scopus.com/pages/publications/105007999427?origin=resultslist | G10: Yes | H10: Excluded
A11: 10 | B11: Precise High-Dimensional Asymptotics for Quantifying Heterogeneous Transfers | C11: 2025 | D11: Scopus | E11: Journal of Machine Learning Research | F11: https://www.scopus.com/pages/publications/105018573290?origin=resultslist | G11: Yes | H11: Excluded
A12: 11 | B12: Time Series Domain Adaptation via Channel-Selective Representation Alignment | C12: 2025 | D12: Scopus | E12: Transactions on Machine Learning Research | F12: https://www.scopus.com/pages/publications/85219504094?origin=resultslist | G12: Yes | H12: Excluded
A13: 12 | B13: Latent Covariate Shift: Unlocking Partial Identifiability for Multi-Source Domain Adaptation | C13: 2025 | D13: Scopus | E13: Transactions on Machine Learning Research | F13: https://www.scopus.com/pages/publications/105005963463?origin=resultslist | G13: Yes | H13: Excluded
... A49: 48 | B49: Hierarchical Graph Attention Network With Bidirectional Lstm For Real-Time Multi-Class Network Intrusion Detection | C49: 2026 | D49: Scopus | E49: Journal of Theoretical and Applied Information Technology | F49: https://www.scopus.com/pages/publications/105045409921?origin=resultslist | G49: Yes | H49: Excluded
A50: 49 | B50: Investigating of Deep Learning-based Approaches for Anomaly Detection in IoT Surveillance Systems | C50: 2023 | D50: WoS | E50: INTERNATIONAL JOURNAL OF ADVANCED COMPUTER SCIENCE AND APPLICATIONS | G50: No | H50: Excluded
A51: 50 | B51: SDN based Intrusion Detection and Prevention Systems using Manufacturer Usage Description: A Survey | C51: 2020 | D51: WoS | E51: INTERNATIONAL JOURNAL OF ADVANCED COMPUTER SCIENCE AND APPLICATIONS | G51: No | H51: Excluded
A52: 51 | B52: A Comprehensive Survey on Intrusion Detection Mechanisms for IoT Based Smart Environments | C52: 2020 | D52: WoS | E52: BIOSCIENCE BIOTECHNOLOGY RESEARCH COMMUNICATIONS | G52: No | H52: Excluded
A53: 52 | B53: Deep Learning Approaches for Intrusion Detection in IIoT Networks - Opportunities and Future Directions | C53: 2021 | D53: WoS | E53: INTERNATIONAL JOURNAL OF ADVANCED COMPUTER SCIENCE AND APPLICATIONS | G53: No | H53: Excluded
A54: 53 | B54: Label Alignment Regularization for Distribution Shift | C54: 2024 | D54: WoS | E54: JOURNAL OF MACHINE LEARNING RESEARCH | G54: No | H54: Excluded
A55: 54 | B55: Gradual Domain Adaptation: Theory and Algorithms | C55: 2024 | D55: WoS | E55: JOURNAL OF MACHINE LEARNING RESEARCH | G55: No | H55: Excluded
A56: 55 | B56: Deep Nonparametric Quantile Regression under Covariate Shift | C56: 2024 | D56: WoS | E56: JOURNAL OF MACHINE LEARNING RESEARCH | G56: No | H56: Excluded
A57: 56 | B57: An EWMA-Based Adaptive Thresholding Concept for Autoencoder-Based Concept Drift Detection in Data Streams EWMA-Based Adaptive Threshold Concept | C57: 2026 | D57: WoS | E57: INTERNATIONAL JOURNAL OF ADVANCED COMPUTER SCIENCE AND APPLICATIONS | G57: No | H57: Excluded
A58: 57 | B58: An Anomaly Detection Model Based on Pearson Correlation Coefficient and Gradient Booster Mechanism | C58: 2024 | D58: WoS | E58: INTERNATIONAL JOURNAL OF ADVANCED COMPUTER SCIENCE AND APPLICATIONS | G58: No | H58: Excluded
A59: 58 | B59: Adaptive Ensemble Models for Robust Intrusion Detection in Cloud Environment on Imbalanced Dataset | C59: 2025 | D59: WoS | E59: INTERNATIONAL JOURNAL OF ADVANCED COMPUTER SCIENCE AND APPLICATIONS | G59: No | H59: Excluded
A60: 59 | B60: Effectiveness of Tree-based Ensembles for Anomaly Discovery: Insights, Batch and Streaming Active Learning | C60: 2024 | D60: WoS | E60: JOURNAL OF ARTIFICIAL INTELLIGENCE RESEARCH | G60: No | H60: Excluded
